Metadata-Version: 1.1
Name: feira-flores
Version: 0.1
Summary: Módulo para gerenciar cadastrados as plantas e flores, com nome e detalhes de como devem ser os cuidados das mesmas.
Home-page: https://github.com/alvesgabriel/feira_flores
Author: Gabriel Alves
Author-email: gabriel.alves.monteiro1@gmail.com
License:                     GNU AFFERO GENERAL PUBLIC LICENSE
